cryptnox_sdk_py/__init__.py
cryptnox_sdk_py/binary_utils.py
cryptnox_sdk_py/connection.py
cryptnox_sdk_py/crypto_utils.py
cryptnox_sdk_py/enums.py
cryptnox_sdk_py/exceptions.py
cryptnox_sdk_py/factory.py
cryptnox_sdk_py/reader.py
cryptnox_sdk_py/card/__init__.py
cryptnox_sdk_py/card/authenticity.py
cryptnox_sdk_py/card/base.py
cryptnox_sdk_py/card/basic_g1.py
cryptnox_sdk_py/card/custom_bits.py
cryptnox_sdk_py/card/nft.py
cryptnox_sdk_py/card/user_data.py
cryptnox_sdk_py/cryptos/__init__.py
cryptnox_sdk_py/cryptos/main.py
cryptnox_sdk_py/cryptos/py2specials.py
cryptnox_sdk_py/cryptos/py3specials.py
cryptnox_sdk_py/cryptos/ripemd.py
cryptnox_sdk_py-1.0.2.dist-info/licenses/LICENSE
cryptnox_sdk_py-1.0.2.dist-info/METADATA
cryptnox_sdk_py-1.0.2.dist-info/WHEEL
cryptnox_sdk_py-1.0.2.dist-info/top_level.txt
cryptnox_sdk_py-1.0.2.dist-info/RECORD
