Metadata-Version: 2.4
Name: cryptnox_sdk_py
Version: 1.0.2
Summary: Python SDK for managing Cryptnox smart card wallets.
Home-page: https://www.cryptnox.com/
Author: Cryptnox SA
Author-email: info@cryptnox.com
License: LGPL-3.0
Project-URL: Source Code, https://github.com/Cryptnox-Software/cryptnox-sdk-py
Keywords: smartcard,hardware,security,cryptography,nfc
Platform: any
Classifier: Development Status :: 5 - Production/Stable
Classifier: Intended Audience :: Developers
Classifier: License :: OSI Approved :: GNU Lesser General Public License v3 (LGPLv3)
Classifier: License :: Other/Proprietary License
Classifier: Operating System :: OS Independent
Classifier: Programming Language :: Python :: 3.11
Classifier: Programming Language :: Python :: 3.12
Classifier: Programming Language :: Python :: 3.13
Classifier: Topic :: Security :: Cryptography
Classifier: Topic :: Software Development :: Libraries :: Python Modules
Classifier: Topic :: System :: Hardware :: Universal Serial Bus (USB) :: Smart Card
Requires-Python: <=3.13.7,>=3.11
License-File: LICENSE
Requires-Dist: aiohttp
Requires-Dist: cryptography
Requires-Dist: pyscard
Dynamic: description
Dynamic: description-content-type
Dynamic: license-file
Dynamic: requires-dist
